pype/__init__.py
pype/__main__.py
pype/_version.py
pype/app.py
pype/asynch.py
pype/cli.py
pype/config.py
pype/interfaces.py
pype/interpret.py
pype/plug.py
pype/traversals.py
pype/utils.py
pype/plugins/__init__.py
pype/plugins/basic.py
python_pype-0.0.88.dist-info/METADATA
python_pype-0.0.88.dist-info/WHEEL
python_pype-0.0.88.dist-info/entry_points.txt
python_pype-0.0.88.dist-info/top_level.txt
python_pype-0.0.88.dist-info/RECORD
