Metadata-Version: 2.1
Name: python-pype
Version: 0.0.88
Summary: An example package. Generated with cookiecutter-pylibrary.
Home-page: http://example.com
Author: pype contributors
Author-email: pype@example.com
License: UNKNOWN
Platform: UNKNOWN
Classifier: Development Status :: 5 - Production/Stable
Classifier: Intended Audience :: Developers
Classifier: Operating System :: Unix
Classifier: Operating System :: POSIX
Classifier: Operating System :: Microsoft :: Windows
Classifier: Programming Language :: Python
Classifier: Programming Language :: Python :: 3.7
Classifier: Programming Language :: Python :: Implementation :: CPython
Classifier: Programming Language :: Python :: Implementation :: PyPy
Classifier: Topic :: Utilities
Requires-Python: >=3.7
Requires-Dist: click
Requires-Dist: toolz
Requires-Dist: attrs
Requires-Dist: click-default-group
Requires-Dist: parso
Requires-Dist: bump2version
Requires-Dist: trio
Requires-Dist: async-generator
Requires-Dist: async-exit-stack
Requires-Dist: appdirs
Requires-Dist: toml
